README
setup.py
django_ljsync.egg-info/PKG-INFO
django_ljsync.egg-info/SOURCES.txt
django_ljsync.egg-info/dependency_links.txt
django_ljsync.egg-info/requires.txt
django_ljsync.egg-info/top_level.txt
ljsync/__init__.py
ljsync/admin.py
ljsync/models.py
ljsync/protocol.py
ljsync/signals.py