Metadata-Version: 1.0
Name: django-ljsync
Version: 0.1.6
Summary: A LiveJournal to Django synchronizer
Home-page: http://bitbucket.org/neithere/django-ljsync/
Author: Andy Mikhailenko
Author-email: andy@neithere.net
License: GNU Lesser General Public License (LGPL), Version 3
Download-URL: http://bitbucket.org/neithere/django-ljsync/src/
Keywords: django livejournal blog sync
Platform: UNKNOWN
Classifier: Development Status :: 2 - Pre-Alpha
Classifier: Environment :: Console
Classifier: Environment :: Web Environment
Classifier: Framework :: Django
Classifier: Intended Audience :: Developers
Classifier: Intended Audience :: System Administrators
Classifier: License :: OSI Approved :: GNU Affero General Public License v3
Classifier: Operating System :: OS Independent
Classifier: Programming Language :: Python
Classifier: Topic :: Communications
Classifier: Topic :: Software Development :: Libraries :: Python Modules
Classifier: Topic :: System :: Recovery Tools
Classifier: Topic :: Utilities
